acumos/__init__.py
acumos/_version.py
acumos/auth.py
acumos/exc.py
acumos/logging.py
acumos/metadata.py
acumos/modeling.py
acumos/pickler.py
acumos/protogen.py
acumos/session.py
acumos/utils.py
acumos/wrapped.py
acumos-1.0.1.dist-info/METADATA
acumos-1.0.1.dist-info/WHEEL
acumos-1.0.1.dist-info/top_level.txt
acumos-1.0.1.dist-info/RECORD
