Metadata-Version: 2.1
Name: acumos
Version: 1.0.1
Summary: Acumos client library for building and pushing Python models
Home-page: https://gerrit.acumos.org/r/gitweb?p=acumos-python-client.git
Author: Paul Triantafyllou
Author-email: trianta@research.att.com
License: Apache License 2.0
Keywords: acumos machine learning model modeling artificial intelligence ml ai
Platform: UNKNOWN
Classifier: Development Status :: 4 - Beta
Classifier: Intended Audience :: Developers
Classifier: Intended Audience :: Science/Research
Classifier: Programming Language :: Python :: 3
Classifier: Programming Language :: Python :: 3.6
Classifier: Programming Language :: Python :: 3.7
Classifier: Programming Language :: Python :: 3.8
Classifier: Programming Language :: Python :: 3.9
Classifier: License :: OSI Approved :: Apache Software License
Requires-Python: >=3.6, <3.10
Requires-Dist: protobuf
Requires-Dist: requests
Requires-Dist: numpy
Requires-Dist: dill
Requires-Dist: appdirs
Requires-Dist: filelock
Requires-Dist: grpcio
Requires-Dist: zipp
Requires-Dist: typing-inspect
